python_pgplot-1.6.1.dist-info/RECORD
python_pgplot-1.6.1.dist-info/WHEEL
python_pgplot-1.6.1.dist-info/top_level.txt
python_pgplot-1.6.1.dist-info/METADATA
ppgplot/_ppgplot.cpython-311-darwin.so
ppgplot/__init__.py
ppgplot/_ppgplot.c
ppgplot/.dylibs/libcpgplot.2.dylib
ppgplot/.dylibs/libcairo.2.dylib
ppgplot/.dylibs/libpgplot.2.dylib
ppgplot/.dylibs/libXrender.1.dylib
ppgplot/.dylibs/libX11.6.dylib
ppgplot/.dylibs/libpng16.16.dylib
ppgplot/.dylibs/libxcb.1.1.0.dylib
ppgplot/.dylibs/libfreetype.6.dylib
ppgplot/.dylibs/libgfortran.5.dylib
ppgplot/.dylibs/libxcb-render.0.0.0.dylib
ppgplot/.dylibs/libXdmcp.6.dylib
ppgplot/.dylibs/libfontconfig.1.dylib
ppgplot/.dylibs/libXau.6.dylib
ppgplot/.dylibs/libXext.6.dylib
ppgplot/.dylibs/libgiza.2.dylib
ppgplot/.dylibs/libpixman-1.0.dylib
ppgplot/.dylibs/libquadmath.0.dylib
ppgplot/.dylibs/libgcc_s.1.1.dylib
ppgplot/.dylibs/libxcb-shm.0.0.0.dylib
