Metadata-Version: 2.4
Name: python-pgplot
Version: 1.6.1
Summary: Python bindings for PGPLOT
Author-email: Marjolein Verkouter <verkouter@jive.eu>
Project-URL: Homepage, https://github.com/haavee/ppgplot
Requires-Python: >=3.9
Requires-Dist: numpy>=1.19.0
